rson/__init__.py
rson/_parser.py
rson/_types.py
rson/rson.py
python_rson-0.1.1.dist-info/LICENSE
python_rson-0.1.1.dist-info/METADATA
python_rson-0.1.1.dist-info/WHEEL
python_rson-0.1.1.dist-info/top_level.txt
python_rson-0.1.1.dist-info/RECORD
