Metadata-Version: 2.1
Name: python-rson
Version: 0.1.1
Summary: Python implementation of RSON (Reference JSON)
Author-email: Xpo Development <dev@xpo.dev>
Project-URL: Homepage, https://github.com/xpodev/python-rson
Project-URL: Issues, https://github.com/xpodev/python-rson/issues
Classifier: Programming Language :: Python :: 3
Classifier: License :: OSI Approved :: MIT License
Classifier: Operating System :: OS Independent
Requires-Python: >=3.8
License-File: LICENSE
